jxmlease/__init__.py
jxmlease/_basenode.py
jxmlease/_parsehandler.py
jxmlease/cdatanode.py
jxmlease/dictnode.py
jxmlease/etreeparser.py
jxmlease/listnode.py
jxmlease/xmlparser.py
jxmlease-1.0.dist-info/DESCRIPTION.rst
jxmlease-1.0.dist-info/METADATA
jxmlease-1.0.dist-info/RECORD
jxmlease-1.0.dist-info/WHEEL
jxmlease-1.0.dist-info/metadata.json
jxmlease-1.0.dist-info/top_level.txt
